rdkix/RDConfig.py
rdkix/RDLogger.py
rdkix/RDPaths.py
rdkix/RDRandom.py
rdkix/TestRunner.py
rdkix/__init__.py
rdkix/conftest.py
rdkix/license.txt
rdkix/pytest.ini
rdkix/rdBase.so
rdkix/Avalon/__init__.py
rdkix/Avalon/pyAvalonTools.so
rdkix/Chem/AllChem.py
rdkix/Chem/BRICS.py
rdkix/Chem/BuildFragmentCatalog.py
rdkix/Chem/ChemicalFeatures.py
rdkix/Chem/ChemicalForceFields.py
rdkix/Chem/Crippen.py
rdkix/Chem/DSViewer.py
rdkix/Chem/Descriptors.py
rdkix/Chem/Descriptors3D.py
rdkix/Chem/EnumerateHeterocycles.py
rdkix/Chem/EnumerateStereoisomers.py
rdkix/Chem/FastSDMolSupplier.py
rdkix/Chem/FeatFinderCLI.py
rdkix/Chem/FilterCatalog.py
rdkix/Chem/FragmentCatalog.py
rdkix/Chem/FragmentMatcher.py
rdkix/Chem/Fragments.py
rdkix/Chem/FunctionalGroups.py
rdkix/Chem/GraphDescriptors.py
rdkix/Chem/Graphs.py
rdkix/Chem/Lipinski.py
rdkix/Chem/MACCSkeys.py
rdkix/Chem/MCS.py
rdkix/Chem/MolCatalog.py
rdkix/Chem/MolSurf.py
rdkix/Chem/PandasPatcher.py
rdkix/Chem/PandasTools.py
rdkix/Chem/PropertyMol.py
rdkix/Chem/PyMol.py
rdkix/Chem/QED.py
rdkix/Chem/Randomize.py
rdkix/Chem/Recap.py
rdkix/Chem/ReducedGraphs.py
rdkix/Chem/RegistrationHash.py
rdkix/Chem/SATIS.py
rdkix/Chem/SaltRemover.py
rdkix/Chem/ShowMols.py
rdkix/Chem/SpacialScore.py
rdkix/Chem/TemplateAlign.py
rdkix/Chem/TorsionFingerprints.py
rdkix/Chem/__init__.py
rdkix/Chem/inchi.py
rdkix/Chem/rdAbbreviations.so
rdkix/Chem/rdCIPLabeler.so
rdkix/Chem/rdChemReactions.so
rdkix/Chem/rdChemicalFeatures.so
rdkix/Chem/rdCoordGen.so
rdkix/Chem/rdDepictor.so
rdkix/Chem/rdDeprotect.so
rdkix/Chem/rdDetermineBonds.so
rdkix/Chem/rdDistGeom.so
rdkix/Chem/rdEHTTools.so
rdkix/Chem/rdFMCS.so
rdkix/Chem/rdFingerprintGenerator.so
rdkix/Chem/rdForceFieldHelpers.so
rdkix/Chem/rdFreeSASA.so
rdkix/Chem/rdGeneralizedSubstruct.so
rdkix/Chem/rdMHFPFingerprint.so
rdkix/Chem/rdMIF.so
rdkix/Chem/rdMMPA.so
rdkix/Chem/rdMolAlign.so
rdkix/Chem/rdMolCatalog.so
rdkix/Chem/rdMolChemicalFeatures.so
rdkix/Chem/rdMolDescriptors.so
rdkix/Chem/rdMolEnumerator.so
rdkit_mux-2024.9.6.dist-info/LICENSE.md
rdkit_mux-2024.9.6.dist-info/METADATA
rdkit_mux-2024.9.6.dist-info/WHEEL
rdkit_mux-2024.9.6.dist-info/top_level.txt
rdkit_mux-2024.9.6.dist-info/RECORD
