Metadata-Version: 2.1
Name: rdkit-mux
Version: 2024.9.6
Summary: An unofficial renamed fork of RDKit library for multiple RDKit versions in single environment.
Home-page: https://github.com/rdkix/rdkix-pypi
Author: Jack Zhou
Author-email: jackzzs@outlook.com
License: BSD-3-Clause
Project-URL: RDKit, http://rdkit.org/
Project-URL: RDKit on Github, https://github.com/rdkit/rdkit
Project-URL: RDKix on Github, https://github.com/rdkix/rdkix
License-File: LICENSE.md
Requires-Dist: numpy
Requires-Dist: Pillow
